{
  "site": {
    "width_m": 1000.0,
    "height_m": 1000.0
  },
  "parcels": [
    {
      "id": "P001",
      "area_px": 14111.0,
      "centroid_norm": [
        0.631714481388633,
        0.8623188054753383
      ],
      "polygon": [
        [
          564.453125,
          969.7265625
        ],
        [
          578.125,
          826.171875
        ],
        [
          596.6796875,
          798.828125
        ],
        [
          624.0234375,
          806.640625
        ],
        [
          679.6875,
          815.4296875
        ],
        [
          721.6796875,
          816.40625
        ],
        [
          726.5625,
          826.171875
        ],
        [
          722.65625,
          829.1015625
        ],
        [
          723.6328125,
          836.9140625
        ],
        [
          692.3828125,
          855.46875
        ],
        [
          688.4765625,
          885.7421875
        ],
        [
          680.6640625,
          899.4140625
        ],
        [
          666.9921875,
          906.25
        ],
        [
          638.671875,
          903.3203125
        ],
        [
          612.3046875,
          903.3203125
        ],
        [
          605.46875,
          906.25
        ],
        [
          598.6328125,
          913.0859375
        ],
        [
          596.6796875,
          934.5703125
        ]
      ]
    },
    {
      "id": "P008",
      "area_px": 333258.0,
      "centroid_norm": [
        0.42108594765073154,
        0.5282172462382748
      ],
      "polygon": [
        [
          904.296875,
          685.546875
        ],
        [
          874.0234375,
          666.9921875
        ],
        [
          766.6015625,
          617.1875
        ],
        [
          747.0703125,
          617.1875
        ],
        [
          677.734375,
          583.984375
        ],
        [
          634.765625,
          572.265625
        ],
        [
          618.1640625,
          573.2421875
        ],
        [
          608.3984375,
          572.265625
        ],
        [
          607.421875,
          569.3359375
        ],
        [
          571.2890625,
          568.359375
        ],
        [
          518.5546875,
          572.265625
        ],
        [
          516.6015625,
          582.03125
        ],
        [
          482.421875,
          581.0546875
        ],
        [
          482.421875,
          575.1953125
        ],
        [
          478.515625,
          573.2421875
        ],
        [
          418.9453125,
          571.2890625
        ],
        [
          416.9921875,
          577.1484375
        ],
        [
          394.53125,
          575.1953125
        ],
        [
          387.6953125,
          580.078125
        ],
        [
          364.2578125,
          570.3125
        ],
        [
          359.375,
          565.4296875
        ],
        [
          345.703125,
          562.5
        ],
        [
          327.1484375,
          563.4765625
        ],
        [
          325.1953125,
          573.2421875
        ],
        [
          330.078125,
          574.21875
        ],
        [
          337.890625,
          583.0078125
        ],
        [
          380.859375,
          592.7734375
        ],
        [
          392.578125,
          592.7734375
        ],
        [
          393.5546875,
          587.890625
        ],
        [
          404.296875,
          591.796875
        ],
        [
          421.875,
          592.7734375
        ],
        [
          422.8515625,
          586.9140625
        ],
        [
          436.5234375,
          586.9140625
        ],
        [
          418.9453125,
          596.6796875
        ],
        [
          419.921875,
          605.46875
        ],
        [
          480.46875,
          606.4453125
        ],
        [
          486.328125,
          616.2109375
        ],
        [
          512.6953125,
          640.625
        ],
        [
          520.5078125,
          652.34375
        ],
        [
          522.4609375,
          675.78125
        ],
        [
          501.953125,
          675.78125
        ],
        [
          491.2109375,
          668.9453125
        ],
        [
          481.4453125,
          668.9453125
        ],
        [
          479.4921875,
          676.7578125
        ],
        [
          497.0703125,
          687.5
        ],
        [
          522.4609375,
          685.546875
        ],
        [
          522.4609375,
          724.609375
        ],
        [
          552.734375,
          794.921875
        ],
        [
          550.78125,
          803.7109375
        ],
        [
          560.546875,
          807.6171875
        ],
        [
          569.3359375,
          807.6171875
        ],
        [
          570.3125,
          798.828125
        ],
        [
          546.875,
          739.2578125
        ],
        [
          596.6796875,
          732.421875
        ],
        [
          598.6328125,
          721.6796875
        ],
        [
          586.9140625,
          720.703125
        ],
        [
          543.9453125,
          727.5390625
        ],
        [
          539.0625,
          604.4921875
        ],
        [
          571.2890625,
          602.5390625
        ],
        [
          572.265625,
          607.421875
        ],
        [
          576.171875,
          609.375
        ],
        [
          624.0234375,
          604.4921875
        ],
        [
          622.0703125,
          616.2109375
        ],
        [
          615.234375,
          617.1875
        ],
        [
          615.234375,
          625.0
        ],
        [
          621.09375,
          625.9765625
        ],
        [
          614.2578125,
          626.953125
        ],
        [
          614.2578125,
          633.7890625
        ],
        [
          624.0234375,
          634.765625
        ],
        [
          624.0234375,
          637.6953125
        ],
        [
          618.1640625,
          639.6484375
        ],
        [
          615.234375,
          655.2734375
        ],
        [
          606.4453125,
          656.25
        ],
        [
          607.421875,
          665.0390625
        ],
        [
          625.9765625,
          673.828125
        ],
        [
          621.09375,
          707.03125
        ],
        [
          602.5390625,
          759.765625
        ],
        [
          566.40625,
          816.40625
        ],
        [
          558.59375,
          823.2421875
        ],
        [
          557.6171875,
          836.9140625
        ],
        [
          560.546875,
          837.890625
        ],
        [
          560.546875,
          848.6328125
        ],
        [
          564.453125,
          855.46875
        ],
        [
          559.5703125,
          856.4453125
        ],
        [
          559.5703125,
          863.28125
        ],
        [
          562.5,
          865.234375
        ],
        [
          556.640625,
          877.9296875
        ],
        [
          556.640625,
          884.765625
        ],
        [
          483.3984375,
          883.7890625
        ],
        [
          392.578125,
          870.1171875
        ],
        [
          374.0234375,
          870.1171875
        ],
        [
          345.703125,
          881.8359375
        ],
        [
          217.7734375,
          843.75
        ],
        [
          160.15625,
          839.84375
        ],
        [
          131.8359375,
          797.8515625
        ],
        [
          102.5390625,
          801.7578125
        ],
        [
          97.65625,
          797.8515625
        ],
        [
          66.40625,
          798.828125
        ],
        [
          49.8046875,
          742.1875
        ],
        [
          66.40625,
          704.1015625
        ],
        [
          68.359375,
          667.96875
        ],
        [
          58.59375,
          645.5078125
        ],
        [
          123.046875,
          623.046875
        ],
        [
          125.9765625,
          614.2578125
        ],
        [
          142.578125,
          607.421875
        ],
        [
          142.578125,
          599.609375
        ],
        [
          138.671875,
          597.65625
        ],
        [
          142.578125,
          596.6796875
        ],
        [
          144.53125,
          602.5390625
        ],
        [
          167.96875,
          598.6328125
        ],
        [
          169.921875,
          586.9140625
        ],
        [
          206.0546875,
          577.1484375
        ],
        [
          188.4765625,
          583.984375
        ],
        [
          188.4765625,
          589.84375
        ],
        [
          196.2890625,
          591.796875
        ],
        [
          259.765625,
          579.1015625
        ],
        [
          264.6484375,
          576.171875
        ],
        [
          264.6484375,
          570.3125
        ],
        [
          249.0234375,
          564.453125
        ],
        [
          262.6953125,
          560.546875
        ],
        [
          262.6953125,
          549.8046875
        ],
        [
          265.625,
          546.875
        ],
        [
          316.40625,
          546.875
        ],
        [
          316.40625,
          537.109375
        ],
        [
          312.5,
          535.15625
        ],
        [
          271.484375,
          535.15625
        ],
        [
          264.6484375,
          531.25
        ],
        [
          266.6015625,
          498.046875
        ],
        [
          315.4296875,
          498.046875
        ],
        [
          318.359375,
          495.1171875
        ],
        [
          318.359375,
          481.4453125
        ],
        [
          315.4296875,
          479.4921875
        ],
        [
          264.6484375,
          477.5390625
        ],
        [
          263.671875,
          455.078125
        ],
        [
          274.4140625,
          444.3359375
        ],
        [
          322.265625,
          446.2890625
        ],
        [
          429.6875,
          458.0078125
        ],
        [
          485.3515625,
          468.75
        ],
        [
          511.71875,
          482.421875
        ],
        [
          540.0390625,
          501.953125
        ],
        [
          594.7265625,
          550.78125
        ],
        [
          602.5390625,
          564.453125
        ],
        [
          615.234375,
          565.4296875
        ],
        [
          617.1875,
          558.59375
        ],
        [
          626.953125,
          562.5
        ],
        [
          635.7421875,
          561.5234375
        ],
        [
          635.7421875,
          554.6875
        ],
        [
          616.2109375,
          538.0859375
        ],
        [
          612.3046875,
          530.2734375
        ],
        [
          534.1796875,
          469.7265625
        ],
        [
          499.0234375,
          452.1484375
        ],
        [
          440.4296875,
          438.4765625
        ],
        [
          252.9296875,
          418.9453125
        ],
        [
          247.0703125,
          402.34375
        ],
        [
          244.140625,
          341.796875
        ],
        [
          244.140625,
          6.8359375
        ],
        [
          329.1015625,
          7.8125
        ],
        [
          522.4609375,
          288.0859375
        ],
        [
          872.0703125,
          565.4296875
        ],
        [
          948.2421875,
          631.8359375
        ]
      ]
    },
    {
      "id": "P010",
      "area_px": 7565.0,
      "centroid_norm": [
        0.676524805849306,
        0.7576779886814277
      ],
      "polygon": [
        [
          716.796875,
          800.78125
        ],
        [
          684.5703125,
          800.78125
        ],
        [
          616.2109375,
          787.109375
        ],
        [
          630.859375,
          761.71875
        ],
        [
          629.8828125,
          751.953125
        ],
        [
          638.671875,
          731.4453125
        ],
        [
          642.578125,
          709.9609375
        ],
        [
          647.4609375,
          708.984375
        ],
        [
          648.4375,
          704.1015625
        ],
        [
          652.34375,
          703.125
        ],
        [
          655.2734375,
          692.3828125
        ],
        [
          667.96875,
          692.3828125
        ],
        [
          668.9453125,
          700.1953125
        ],
        [
          676.7578125,
          699.21875
        ],
        [
          676.7578125,
          692.3828125
        ],
        [
          672.8515625,
          690.4296875
        ],
        [
          670.8984375,
          678.7109375
        ],
        [
          666.9921875,
          673.828125
        ],
        [
          673.828125,
          673.828125
        ],
        [
          686.5234375,
          682.6171875
        ],
        [
          682.6171875,
          697.265625
        ],
        [
          678.7109375,
          698.2421875
        ],
        [
          678.7109375,
          705.078125
        ],
        [
          670.8984375,
          707.03125
        ],
        [
          668.9453125,
          713.8671875
        ],
        [
          663.0859375,
          713.8671875
        ],
        [
          656.25,
          720.703125
        ],
        [
          656.25,
          725.5859375
        ],
        [
          647.4609375,
          726.5625
        ],
        [
          642.578125,
          731.4453125
        ],
        [
          640.625,
          741.2109375
        ],
        [
          649.4140625,
          743.1640625
        ],
        [
          656.25,
          735.3515625
        ],
        [
          666.015625,
          735.3515625
        ],
        [
          666.9921875,
          728.515625
        ],
        [
          695.3125,
          730.46875
        ],
        [
          698.2421875,
          721.6796875
        ],
        [
          714.84375,
          724.609375
        ],
        [
          710.9375,
          725.5859375
        ],
        [
          710.9375,
          732.421875
        ],
        [
          724.609375,
          742.1875
        ],
        [
          721.6796875,
          758.7890625
        ],
        [
          734.375,
          766.6015625
        ],
        [
          734.375,
          771.484375
        ],
        [
          722.65625,
          784.1796875
        ]
      ]
    }
  ]
}