{
  "site": {
    "width_m": 1000.0,
    "height_m": 1000.0
  },
  "parcels": [
    {
      "id": "P002",
      "area_px": 18230.0,
      "centroid_norm": [
        0.4738755335470379,
        0.9228936677180472
      ],
      "polygon": [
        [
          366.2109375,
          856.4453125
        ],
        [
          417.96875,
          858.3984375
        ],
        [
          417.96875,
          864.2578125
        ],
        [
          425.78125,
          874.0234375
        ],
        [
          454.1015625,
          890.625
        ],
        [
          454.1015625,
          907.2265625
        ],
        [
          447.265625,
          909.1796875
        ],
        [
          447.265625,
          916.015625
        ],
        [
          459.9609375,
          917.96875
        ],
        [
          470.703125,
          925.78125
        ],
        [
          473.6328125,
          931.640625
        ],
        [
          484.375,
          930.6640625
        ],
        [
          483.3984375,
          917.96875
        ],
        [
          469.7265625,
          910.15625
        ],
        [
          469.7265625,
          881.8359375
        ],
        [
          478.515625,
          874.0234375
        ],
        [
          496.09375,
          876.953125
        ],
        [
          487.3046875,
          876.953125
        ],
        [
          486.328125,
          885.7421875
        ],
        [
          493.1640625,
          886.71875
        ],
        [
          499.0234375,
          893.5546875
        ],
        [
          509.765625,
          893.5546875
        ],
        [
          512.6953125,
          889.6484375
        ],
        [
          522.4609375,
          887.6953125
        ],
        [
          521.484375,
          880.859375
        ],
        [
          512.6953125,
          880.859375
        ],
        [
          509.765625,
          884.765625
        ],
        [
          502.9296875,
          877.9296875
        ],
        [
          598.6328125,
          883.7890625
        ],
        [
          599.609375,
          886.71875
        ],
        [
          594.7265625,
          889.6484375
        ],
        [
          585.9375,
          907.2265625
        ],
        [
          583.0078125,
          936.5234375
        ],
        [
          565.4296875,
          939.453125
        ],
        [
          533.203125,
          951.171875
        ],
        [
          534.1796875,
          959.9609375
        ],
        [
          543.9453125,
          959.9609375
        ],
        [
          541.9921875,
          968.75
        ],
        [
          536.1328125,
          965.8203125
        ],
        [
          523.4375,
          965.8203125
        ],
        [
          522.4609375,
          968.75
        ],
        [
          430.6640625,
          982.421875
        ],
        [
          416.9921875,
          992.1875
        ],
        [
          393.5546875,
          976.5625
        ],
        [
          390.625,
          970.703125
        ],
        [
          390.625,
          947.265625
        ],
        [
          398.4375,
          929.6875
        ],
        [
          398.4375,
          921.875
        ],
        [
          384.765625,
          887.6953125
        ],
        [
          366.2109375,
          869.140625
        ]
      ]
    },
    {
      "id": "P007",
      "area_px": 12600.0,
      "centroid_norm": [
        0.5087740265376984,
        0.7560931299603175
      ],
      "polygon": [
        [
          454.1015625,
          875.9765625
        ],
        [
          461.9140625,
          868.1640625
        ],
        [
          461.9140625,
          861.328125
        ],
        [
          453.125,
          855.46875
        ],
        [
          437.5,
          854.4921875
        ],
        [
          434.5703125,
          851.5625
        ],
        [
          477.5390625,
          847.65625
        ],
        [
          475.5859375,
          833.984375
        ],
        [
          483.3984375,
          833.0078125
        ],
        [
          480.46875,
          806.640625
        ],
        [
          486.328125,
          806.640625
        ],
        [
          490.234375,
          833.984375
        ],
        [
          503.90625,
          835.9375
        ],
        [
          504.8828125,
          826.171875
        ],
        [
          500.0,
          810.546875
        ],
        [
          501.953125,
          804.6875
        ],
        [
          521.484375,
          804.6875
        ],
        [
          523.4375,
          811.5234375
        ],
        [
          533.203125,
          811.5234375
        ],
        [
          535.15625,
          804.6875
        ],
        [
          546.875,
          804.6875
        ],
        [
          548.828125,
          795.8984375
        ],
        [
          519.53125,
          793.9453125
        ],
        [
          519.53125,
          782.2265625
        ],
        [
          500.0,
          758.7890625
        ],
        [
          492.1875,
          758.7890625
        ],
        [
          489.2578125,
          765.625
        ],
        [
          482.421875,
          766.6015625
        ],
        [
          482.421875,
          774.4140625
        ],
        [
          494.140625,
          784.1796875
        ],
        [
          498.046875,
          793.9453125
        ],
        [
          484.375,
          795.8984375
        ],
        [
          482.421875,
          791.9921875
        ],
        [
          476.5625,
          791.9921875
        ],
        [
          476.5625,
          783.203125
        ],
        [
          468.75,
          769.53125
        ],
        [
          479.4921875,
          769.53125
        ],
        [
          476.5625,
          755.859375
        ],
        [
          465.8203125,
          754.8828125
        ],
        [
          464.84375,
          764.6484375
        ],
        [
          458.0078125,
          765.625
        ],
        [
          455.078125,
          758.7890625
        ],
        [
          473.6328125,
          748.046875
        ],
        [
          506.8359375,
          742.1875
        ],
        [
          509.765625,
          733.3984375
        ],
        [
          499.0234375,
          731.4453125
        ],
        [
          493.1640625,
          735.3515625
        ],
        [
          469.7265625,
          738.28125
        ],
        [
          475.5859375,
          729.4921875
        ],
        [
          476.5625,
          718.75
        ],
        [
          485.3515625,
          717.7734375
        ],
        [
          486.328125,
          709.9609375
        ],
        [
          478.515625,
          707.03125
        ],
        [
          432.6171875,
          705.078125
        ],
        [
          433.59375,
          691.40625
        ],
        [
          448.2421875,
          676.7578125
        ],
        [
          472.65625,
          664.0625
        ],
        [
          472.65625,
          660.15625
        ],
        [
          478.515625,
          656.25
        ],
        [
          477.5390625,
          642.578125
        ],
        [
          480.46875,
          633.7890625
        ],
        [
          503.90625,
          633.7890625
        ],
        [
          510.7421875,
          636.71875
        ],
        [
          512.6953125,
          643.5546875
        ],
        [
          525.390625,
          653.3203125
        ],
        [
          533.203125,
          652.34375
        ],
        [
          534.1796875,
          644.53125
        ],
        [
          547.8515625,
          643.5546875
        ],
        [
          550.78125,
          636.71875
        ],
        [
          547.8515625,
          652.34375
        ],
        [
          539.0625,
          653.3203125
        ],
        [
          523.4375,
          661.1328125
        ],
        [
          511.71875,
          670.8984375
        ],
        [
          510.7421875,
          675.78125
        ],
        [
          503.90625,
          678.7109375
        ],
        [
          503.90625,
          682.6171875
        ],
        [
          486.328125,
          683.59375
        ],
        [
          484.375,
          692.3828125
        ],
        [
          500.9765625,
          693.359375
        ],
        [
          504.8828125,
          700.1953125
        ],
        [
          493.1640625,
          703.125
        ],
        [
          493.1640625,
          712.890625
        ],
        [
          508.7890625,
          710.9375
        ],
        [
          510.7421875,
          714.84375
        ],
        [
          521.484375,
          714.84375
        ],
        [
          526.3671875,
          719.7265625
        ],
        [
          530.2734375,
          734.375
        ],
        [
          536.1328125,
          742.1875
        ],
        [
          584.9609375,
          854.4921875
        ],
        [
          574.21875,
          856.4453125
        ],
        [
          574.21875,
          862.3046875
        ],
        [
          581.0546875,
          864.2578125
        ],
        [
          571.2890625,
          863.28125
        ],
        [
          566.40625,
          868.1640625
        ],
        [
          554.6875,
          870.1171875
        ],
        [
          553.7109375,
          861.328125
        ],
        [
          538.0859375,
          859.375
        ],
        [
          536.1328125,
          857.421875
        ],
        [
          541.9921875,
          854.4921875
        ],
        [
          541.9921875,
          847.65625
        ],
        [
          527.34375,
          829.1015625
        ],
        [
          527.34375,
          820.3125
        ],
        [
          512.6953125,
          818.359375
        ],
        [
          511.71875,
          830.078125
        ],
        [
          524.4140625,
          847.65625
        ],
        [
          517.578125,
          849.609375
        ],
        [
          511.71875,
          839.84375
        ],
        [
          503.90625,
          838.8671875
        ],
        [
          500.9765625,
          840.8203125
        ],
        [
          500.9765625,
          849.609375
        ],
        [
          504.8828125,
          856.4453125
        ],
        [
          493.1640625,
          840.8203125
        ],
        [
          484.375,
          840.8203125
        ],
        [
          482.421875,
          850.5859375
        ],
        [
          486.328125,
          855.46875
        ],
        [
          473.6328125,
          854.4921875
        ],
        [
          472.65625,
          863.28125
        ],
        [
          465.8203125,
          863.28125
        ],
        [
          460.9375,
          872.0703125
        ]
      ]
    },
    {
      "id": "P015",
      "area_px": 6906.0,
      "centroid_norm": [
        0.3956857035548798,
        0.7603029747683174
      ],
      "polygon": [
        [
          471.6796875,
          797.8515625
        ],
        [
          419.921875,
          800.78125
        ],
        [
          402.34375,
          806.640625
        ],
        [
          391.6015625,
          804.6875
        ],
        [
          389.6484375,
          813.4765625
        ],
        [
          395.5078125,
          815.4296875
        ],
        [
          395.5078125,
          820.3125
        ],
        [
          389.6484375,
          825.1953125
        ],
        [
          390.625,
          833.984375
        ],
        [
          375.9765625,
          834.9609375
        ],
        [
          375.0,
          843.75
        ],
        [
          372.0703125,
          843.75
        ],
        [
          373.046875,
          804.6875
        ],
        [
          385.7421875,
          803.7109375
        ],
        [
          385.7421875,
          796.875
        ],
        [
          380.859375,
          792.96875
        ],
        [
          384.765625,
          791.015625
        ],
        [
          384.765625,
          785.15625
        ],
        [
          375.0,
          784.1796875
        ],
        [
          375.9765625,
          769.53125
        ],
        [
          360.3515625,
          762.6953125
        ],
        [
          356.4453125,
          753.90625
        ],
        [
          357.421875,
          740.234375
        ],
        [
          346.6796875,
          732.421875
        ],
        [
          345.703125,
          724.609375
        ],
        [
          339.84375,
          718.75
        ],
        [
          341.796875,
          708.0078125
        ],
        [
          396.484375,
          709.9609375
        ],
        [
          420.8984375,
          716.796875
        ],
        [
          420.8984375,
          738.28125
        ],
        [
          425.78125,
          741.2109375
        ],
        [
          428.7109375,
          757.8125
        ],
        [
          407.2265625,
          759.765625
        ],
        [
          398.4375,
          755.859375
        ],
        [
          386.71875,
          755.859375
        ],
        [
          385.7421875,
          763.671875
        ],
        [
          399.4140625,
          768.5546875
        ],
        [
          379.8828125,
          767.578125
        ],
        [
          377.9296875,
          775.390625
        ],
        [
          400.390625,
          777.34375
        ],
        [
          405.2734375,
          775.390625
        ],
        [
          405.2734375,
          770.5078125
        ],
        [
          424.8046875,
          768.5546875
        ],
        [
          407.2265625,
          778.3203125
        ],
        [
          409.1796875,
          786.1328125
        ],
        [
          416.9921875,
          786.1328125
        ],
        [
          431.640625,
          777.34375
        ],
        [
          442.3828125,
          775.390625
        ],
        [
          445.3125,
          771.484375
        ],
        [
          457.03125,
          771.484375
        ],
        [
          464.84375,
          794.921875
        ]
      ]
    },
    {
      "id": "P022",
      "area_px": 181615.0,
      "centroid_norm": [
        0.4897704278280979,
        0.3638158899406023
      ],
      "polygon": [
        [
          331.0546875,
          695.3125
        ],
        [
          298.828125,
          662.109375
        ],
        [
          292.96875,
          629.8828125
        ],
        [
          284.1796875,
          620.1171875
        ],
        [
          283.203125,
          585.9375
        ],
        [
          312.5,
          580.078125
        ],
        [
          334.9609375,
          570.3125
        ],
        [
          342.7734375,
          564.453125
        ],
        [
          357.421875,
          543.9453125
        ],
        [
          356.4453125,
          535.15625
        ],
        [
          344.7265625,
          526.3671875
        ],
        [
          322.265625,
          523.4375
        ],
        [
          298.828125,
          513.671875
        ],
        [
          317.3828125,
          477.5390625
        ],
        [
          340.8203125,
          472.65625
        ],
        [
          342.7734375,
          465.8203125
        ],
        [
          360.3515625,
          459.9609375
        ],
        [
          364.2578125,
          455.078125
        ],
        [
          365.234375,
          423.828125
        ],
        [
          370.1171875,
          415.0390625
        ],
        [
          375.0,
          412.109375
        ],
        [
          399.4140625,
          412.109375
        ],
        [
          456.0546875,
          418.9453125
        ],
        [
          502.9296875,
          441.40625
        ],
        [
          509.765625,
          449.21875
        ],
        [
          522.4609375,
          455.078125
        ],
        [
          529.296875,
          462.890625
        ],
        [
          531.25,
          470.703125
        ],
        [
          545.8984375,
          475.5859375
        ],
        [
          553.7109375,
          475.5859375
        ],
        [
          555.6640625,
          468.75
        ],
        [
          561.5234375,
          471.6796875
        ],
        [
          568.359375,
          470.703125
        ],
        [
          566.40625,
          460.9375
        ],
        [
          560.546875,
          454.1015625
        ],
        [
          556.640625,
          454.1015625
        ],
        [
          550.78125,
          444.3359375
        ],
        [
          507.8125,
          415.0390625
        ],
        [
          475.5859375,
          402.34375
        ],
        [
          407.2265625,
          389.6484375
        ],
        [
          390.625,
          389.6484375
        ],
        [
          358.3984375,
          397.4609375
        ],
        [
          337.890625,
          398.4375
        ],
        [
          322.265625,
          409.1796875
        ],
        [
          316.40625,
          417.96875
        ],
        [
          264.6484375,
          338.8671875
        ],
        [
          272.4609375,
          329.1015625
        ],
        [
          280.2734375,
          288.0859375
        ],
        [
          293.9453125,
          254.8828125
        ],
        [
          320.3125,
          233.3984375
        ],
        [
          321.2890625,
          224.609375
        ],
        [
          335.9375,
          205.078125
        ],
        [
          356.4453125,
          209.9609375
        ],
        [
          380.859375,
          191.40625
        ],
        [
          390.625,
          166.015625
        ],
        [
          408.203125,
          138.671875
        ],
        [
          427.734375,
          140.625
        ],
        [
          441.40625,
          136.71875
        ],
        [
          445.3125,
          122.0703125
        ],
        [
          443.359375,
          106.4453125
        ],
        [
          457.03125,
          94.7265625
        ],
        [
          458.984375,
          86.9140625
        ],
        [
          468.75,
          80.078125
        ],
        [
          488.28125,
          50.78125
        ],
        [
          501.953125,
          13.671875
        ],
        [
          514.6484375,
          24.4140625
        ],
        [
          527.34375,
          57.6171875
        ],
        [
          542.96875,
          59.5703125
        ],
        [
          558.59375,
          67.3828125
        ],
        [
          569.3359375,
          82.03125
        ],
        [
          591.796875,
          94.7265625
        ],
        [
          607.421875,
          130.859375
        ],
        [
          619.140625,
          139.6484375
        ],
        [
          624.0234375,
          153.3203125
        ],
        [
          638.671875,
          168.9453125
        ],
        [
          663.0859375,
          176.7578125
        ],
        [
          662.109375,
          200.1953125
        ],
        [
          676.7578125,
          230.46875
        ],
        [
          687.5,
          264.6484375
        ],
        [
          684.5703125,
          277.34375
        ],
        [
          685.546875,
          300.78125
        ],
        [
          710.9375,
          317.3828125
        ],
        [
          720.703125,
          347.65625
        ],
        [
          730.46875,
          366.2109375
        ],
        [
          725.5859375,
          404.296875
        ],
        [
          735.3515625,
          423.828125
        ],
        [
          729.4921875,
          450.1953125
        ],
        [
          700.1953125,
          461.9140625
        ],
        [
          687.5,
          455.078125
        ],
        [
          681.640625,
          455.078125
        ],
        [
          679.6875,
          462.890625
        ],
        [
          675.78125,
          463.8671875
        ],
        [
          662.109375,
          443.359375
        ],
        [
          653.3203125,
          444.3359375
        ],
        [
          646.484375,
          438.4765625
        ],
        [
          646.484375,
          420.8984375
        ],
        [
          635.7421875,
          418.9453125
        ],
        [
          629.8828125,
          424.8046875
        ],
        [
          629.8828125,
          435.546875
        ],
        [
          636.71875,
          458.0078125
        ],
        [
          622.0703125,
          456.0546875
        ],
        [
          620.1171875,
          463.8671875
        ],
        [
          612.3046875,
          463.8671875
        ],
        [
          606.4453125,
          467.7734375
        ],
        [
          607.421875,
          474.609375
        ],
        [
          594.7265625,
          476.5625
        ],
        [
          591.796875,
          491.2109375
        ],
        [
          583.984375,
          492.1875
        ],
        [
          585.9375,
          500.9765625
        ],
        [
          594.7265625,
          501.953125
        ],
        [
          586.9140625,
          511.71875
        ],
        [
          586.9140625,
          522.4609375
        ],
        [
          589.84375,
          525.390625
        ],
        [
          597.65625,
          525.390625
        ],
        [
          599.609375,
          522.4609375
        ],
        [
          623.046875,
          524.4140625
        ],
        [
          625.0,
          543.9453125
        ],
        [
          634.765625,
          543.9453125
        ],
        [
          635.7421875,
          537.109375
        ],
        [
          644.53125,
          537.109375
        ],
        [
          650.390625,
          521.484375
        ],
        [
          674.8046875,
          508.7890625
        ],
        [
          674.8046875,
          503.90625
        ],
        [
          679.6875,
          502.9296875
        ],
        [
          680.6640625,
          532.2265625
        ],
        [
          675.78125,
          550.78125
        ],
        [
          649.4140625,
          562.5
        ],
        [
          645.5078125,
          569.3359375
        ],
        [
          645.5078125,
          579.1015625
        ],
        [
          588.8671875,
          577.1484375
        ],
        [
          588.8671875,
          561.5234375
        ],
        [
          584.9609375,
          559.5703125
        ],
        [
          592.7734375,
          553.7109375
        ],
        [
          595.703125,
          531.25
        ],
        [
          582.03125,
          532.2265625
        ],
        [
          579.1015625,
          528.3203125
        ],
        [
          571.2890625,
          527.34375
        ],
        [
          583.0078125,
          527.34375
        ],
        [
          583.984375,
          519.53125
        ],
        [
          581.0546875,
          517.578125
        ],
        [
          554.6875,
          515.625
        ],
        [
          554.6875,
          530.2734375
        ],
        [
          544.921875,
          530.2734375
        ],
        [
          543.9453125,
          537.109375
        ],
        [
          533.203125,
          537.109375
        ],
        [
          532.2265625,
          543.9453125
        ],
        [
          512.6953125,
          547.8515625
        ],
        [
          499.0234375,
          512.6953125
        ],
        [
          485.3515625,
          499.0234375
        ],
        [
          476.5625,
          499.0234375
        ],
        [
          475.5859375,
          501.953125
        ],
        [
          457.03125,
          493.1640625
        ],
        [
          440.4296875,
          490.234375
        ],
        [
          404.296875,
          471.6796875
        ],
        [
          389.6484375,
          458.984375
        ],
        [
          378.90625,
          458.984375
        ],
        [
          377.9296875,
          468.75
        ],
        [
          393.5546875,
          481.4453125
        ],
        [
          441.40625,
          505.859375
        ],
        [
          458.984375,
          508.7890625
        ],
        [
          468.75,
          517.578125
        ],
        [
          471.6796875,
          526.3671875
        ],
        [
          464.84375,
          536.1328125
        ],
        [
          464.84375,
          545.8984375
        ],
        [
          467.7734375,
          547.8515625
        ],
        [
          458.0078125,
          549.8046875
        ],
        [
          452.1484375,
          576.171875
        ],
        [
          454.1015625,
          584.9609375
        ],
        [
          489.2578125,
          588.8671875
        ],
        [
          491.2109375,
          581.0546875
        ],
        [
          500.9765625,
          581.0546875
        ],
        [
          517.578125,
          558.59375
        ],
        [
          529.296875,
          559.5703125
        ],
        [
          529.296875,
          562.5
        ],
        [
          522.4609375,
          570.3125
        ],
        [
          513.671875,
          570.3125
        ],
        [
          511.71875,
          578.125
        ],
        [
          532.2265625,
          581.0546875
        ],
        [
          545.8984375,
          560.546875
        ],
        [
          558.59375,
          552.734375
        ],
        [
          559.5703125,
          556.640625
        ],
        [
          565.4296875,
          557.6171875
        ],
        [
          562.5,
          572.265625
        ],
        [
          535.15625,
          579.1015625
        ],
        [
          526.3671875,
          585.9375
        ],
        [
          504.8828125,
          593.75
        ],
        [
          505.859375,
          602.5390625
        ],
        [
          514.6484375,
          602.5390625
        ],
        [
          534.1796875,
          595.703125
        ],
        [
          545.8984375,
          587.890625
        ],
        [
          561.5234375,
          583.984375
        ],
        [
          558.59375,
          605.46875
        ],
        [
          553.7109375,
          621.09375
        ],
        [
          544.921875,
          624.0234375
        ],
        [
          503.90625,
          620.1171875
        ],
        [
          479.4921875,
          621.09375
        ],
        [
          480.46875,
          609.375
        ],
        [
          466.796875,
          607.421875
        ],
        [
          460.9375,
          618.1640625
        ],
        [
          460.9375,
          648.4375
        ],
        [
          451.171875,
          643.5546875
        ],
        [
          440.4296875,
          643.5546875
        ],
        [
          432.6171875,
          647.4609375
        ],
        [
          433.59375,
          655.2734375
        ],
        [
          445.3125,
          654.296875
        ],
        [
          446.2890625,
          657.2265625
        ],
        [
          422.8515625,
          670.8984375
        ],
        [
          422.8515625,
          676.7578125
        ],
        [
          414.0625,
          685.546875
        ],
        [
          414.0625,
          692.3828125
        ],
        [
          419.921875,
          695.3125
        ],
        [
          417.96875,
          702.1484375
        ],
        [
          406.25,
          699.21875
        ]
      ]
    },
    {
      "id": "P027",
      "area_px": 1662.0,
      "centroid_norm": [
        0.6031583746991577,
        0.609881496314681
      ],
      "polygon": [
        [
          588.8671875,
          653.3203125
        ],
        [
          588.8671875,
          647.4609375
        ],
        [
          592.7734375,
          644.53125
        ],
        [
          592.7734375,
          626.953125
        ],
        [
          588.8671875,
          615.234375
        ],
        [
          581.0546875,
          613.28125
        ],
        [
          584.9609375,
          588.8671875
        ],
        [
          643.5546875,
          588.8671875
        ],
        [
          637.6953125,
          597.65625
        ],
        [
          609.375,
          602.5390625
        ],
        [
          610.3515625,
          611.328125
        ],
        [
          601.5625,
          625.0
        ],
        [
          605.46875,
          645.5078125
        ],
        [
          598.6328125,
          653.3203125
        ]
      ]
    }
  ]
}